{
  "id": "quantum-foundations/index",
  "title": "Quantum Foundations Overview",
  "description": "This is the overview page for Quantum Foundations.",
  "source": "@site/docs/quantum-foundations/index.md",
  "sourceDirName": "quantum-foundations",
  "slug": "/quantum-foundations/",
  "permalink": "/goblin-quantum-lab/docs/quantum-foundations/",
  "draft": false,
  "unlisted": false,
  "editUrl": "https://github.com/Goblin-Quantum-Lab/goblin-quantum-lab/tree/main/docs/quantum-foundations/index.md",
  "tags": [],
  "version": "current",
  "frontMatter": {},
  "sidebar": "tutorialSidebar",
  "previous": {
    "title": "Learning Pathways Overview",
    "permalink": "/goblin-quantum-lab/docs/learning-pathways/"
  },
  "next": {
    "title": "Labs Overview",
    "permalink": "/goblin-quantum-lab/docs/labs/"
  }
}